odoo10_addon_partner_address_version-10.0.2.0.0-py3.8-nspkg.pth
odoo/addons/partner_address_version/README.rst
odoo/addons/partner_address_version/__init__.py
odoo/addons/partner_address_version/__manifest__.py
odoo/addons/partner_address_version/i18n/partner_address_version.pot
odoo/addons/partner_address_version/models/__init__.py
odoo/addons/partner_address_version/models/res_partner.py
odoo/addons/partner_address_version/readme/CONTRIBUTORS.rst
odoo/addons/partner_address_version/readme/DESCRIPTION.rst
odoo/addons/partner_address_version/static/description/icon.png
odoo/addons/partner_address_version/static/description/index.html
odoo/addons/partner_address_version/tests/__init__.py
odoo/addons/partner_address_version/tests/test_address_version.py
odoo/addons/partner_address_version/wizards/__init__.py
odoo/addons/partner_address_version/wizards/base_partner_merge.py
odoo10_addon_partner_address_version-10.0.2.0.0.dist-info/METADATA
odoo10_addon_partner_address_version-10.0.2.0.0.dist-info/WHEEL
odoo10_addon_partner_address_version-10.0.2.0.0.dist-info/namespace_packages.txt
odoo10_addon_partner_address_version-10.0.2.0.0.dist-info/top_level.txt
odoo10_addon_partner_address_version-10.0.2.0.0.dist-info/RECORD
